lmt8x/__init__.py
lmt8x/lmt84.py
lmt8x/lmt85.py
lmt8x/lmt86.py
lmt8x/lmt87.py
lmt8x-1.0.0.dist-info/AUTHORS.rst
lmt8x-1.0.0.dist-info/LICENSE
lmt8x-1.0.0.dist-info/METADATA
lmt8x-1.0.0.dist-info/WHEEL
lmt8x-1.0.0.dist-info/top_level.txt
lmt8x-1.0.0.dist-info/RECORD
